fetchcode_container/__init__.py
fetchcode_container/bin/default-policy.json
fetchcode_container/bin/skopeo
fetchcode_container/licenses/apache-2.0.LICENSE
fetchcode_container-1.2.3.210512.dist-info/METADATA
fetchcode_container-1.2.3.210512.dist-info/README.rst
fetchcode_container-1.2.3.210512.dist-info/WHEEL
fetchcode_container-1.2.3.210512.dist-info/apache-2.0.LICENSE
fetchcode_container-1.2.3.210512.dist-info/entry_points.txt
fetchcode_container-1.2.3.210512.dist-info/fetchcode_container.ABOUT
fetchcode_container-1.2.3.210512.dist-info/top_level.txt
fetchcode_container-1.2.3.210512.dist-info/RECORD
